cs/debug.py
cs_debug-20250728.dist-info/WHEEL
cs_debug-20250728.dist-info/METADATA
cs_debug-20250728.dist-info/RECORD
